MANIFEST.in
README.md
setup.cfg
setup.py
company_name_cleaner.egg-info/PKG-INFO
company_name_cleaner.egg-info/SOURCES.txt
company_name_cleaner.egg-info/dependency_links.txt
company_name_cleaner.egg-info/namespace_packages.txt
company_name_cleaner.egg-info/not-zip-safe
company_name_cleaner.egg-info/requires.txt
company_name_cleaner.egg-info/top_level.txt
fingerprints/__init__.py
fingerprints/cleanup.py
fingerprints/constants.py
fingerprints/generate.py
fingerprints/py.typed
fingerprints/replacers.py
fingerprints/types.json