Metadata-Version: 2.1
Name: company-name-cleaner
Version: 1.0.3
Summary: A library to generate entity fingerprints.
Home-page: https://github.com/dulatus/fingerprints
Author: Friedrich Lindenberg
Author-email: friedrich@pudo.org
License: MIT
Keywords: names people companies normalisation iso20275
Platform: UNKNOWN
Classifier: Intended Audience :: Developers
Classifier: License :: OSI Approved :: MIT License
Classifier: Operating System :: OS Independent
Classifier: Programming Language :: Python :: 3.4
Classifier: Programming Language :: Python :: 3.5
Classifier: Programming Language :: Python :: 3.6
